ndjson/__init__.py
ndjson/api.py
ndjson/codecs.py
ndjson-0.3.0.dist-info/DESCRIPTION.rst
ndjson-0.3.0.dist-info/METADATA
ndjson-0.3.0.dist-info/RECORD
ndjson-0.3.0.dist-info/WHEEL
ndjson-0.3.0.dist-info/metadata.json
ndjson-0.3.0.dist-info/top_level.txt
ndjson-0.3.0.dist-info/zip-safe
