Metadata-Version: 2.0
Name: ndjson
Version: 0.3.0
Summary: JsonDecoder for ndjson
Home-page: https://github.com/rhgrant10/ndjson
Author: Robert Grant
Author-email: rhgrant10@gmail.com
License: GNU General Public License v3
Keywords: ndjson
Platform: UNKNOWN
Classifier: Development Status :: 2 - Pre-Alpha
Classifier: Intended Audience :: Developers
Classifier: License :: OSI Approved :: GNU General Public License v3 (GPLv3)
Classifier: Natural Language :: English
Classifier: Programming Language :: Python :: 2
Classifier: Programming Language :: Python :: 2.7
Classifier: Programming Language :: Python :: 3
Classifier: Programming Language :: Python :: 3.5
Classifier: Programming Language :: Python :: 3.6
Classifier: Programming Language :: Python :: 3.7
